{
    "id": "kriyam_0340_C2",
    "model": "FFDN",
    "confidence": 0.9814,
    "regions": [
        {
            "x": 1353,
            "y": 997,
            "w": 30,
            "h": 27,
            "area": 717,
            "ratio": 8.2e-05,
            "confidence": 0.9814
        },
        {
            "x": 1805,
            "y": 1344,
            "w": 5,
            "h": 5,
            "area": 25,
            "ratio": 3e-06,
            "confidence": 0.7126
        },
        {
            "x": 1339,
            "y": 1397,
            "w": 8,
            "h": 11,
            "area": 78,
            "ratio": 9e-06,
            "confidence": 0.8618
        },
        {
            "x": 201,
            "y": 2393,
            "w": 22,
            "h": 31,
            "area": 657,
            "ratio": 7.5e-05,
            "confidence": 0.9711
        },
        {
            "x": 1339,
            "y": 2525,
            "w": 5,
            "h": 5,
            "area": 25,
            "ratio": 3e-06,
            "confidence": 0.8377
        },
        {
            "x": 987,
            "y": 3457,
            "w": 7,
            "h": 10,
            "area": 63,
            "ratio": 7e-06,
            "confidence": 0.8283
        }
    ]
}