{
    "id": "kriyam_0568_C0",
    "model": "FFDN",
    "confidence": 1.0,
    "regions": [
        {
            "x": 1617,
            "y": 20,
            "w": 82,
            "h": 43,
            "area": 3357,
            "ratio": 0.000556,
            "confidence": 0.9999
        },
        {
            "x": 876,
            "y": 52,
            "w": 148,
            "h": 59,
            "area": 7664,
            "ratio": 0.00127,
            "confidence": 0.9959
        },
        {
            "x": 325,
            "y": 108,
            "w": 7,
            "h": 5,
            "area": 35,
            "ratio": 6e-06,
            "confidence": 0.7575
        },
        {
            "x": 350,
            "y": 118,
            "w": 100,
            "h": 22,
            "area": 1687,
            "ratio": 0.000279,
            "confidence": 0.9237
        },
        {
            "x": 309,
            "y": 124,
            "w": 33,
            "h": 19,
            "area": 449,
            "ratio": 7.4e-05,
            "confidence": 0.9702
        },
        {
            "x": 1342,
            "y": 272,
            "w": 225,
            "h": 63,
            "area": 8540,
            "ratio": 0.001415,
            "confidence": 0.9999
        },
        {
            "x": 1721,
            "y": 305,
            "w": 186,
            "h": 90,
            "area": 6713,
            "ratio": 0.001112,
            "confidence": 0.9996
        },
        {
            "x": 1900,
            "y": 325,
            "w": 7,
            "h": 17,
            "area": 102,
            "ratio": 1.7e-05,
            "confidence": 0.9701
        },
        {
            "x": 1233,
            "y": 417,
            "w": 21,
            "h": 10,
            "area": 188,
            "ratio": 3.1e-05,
            "confidence": 0.9356
        },
        {
            "x": 245,
            "y": 605,
            "w": 78,
            "h": 42,
            "area": 3275,
            "ratio": 0.000543,
            "confidence": 1.0
        },
        {
            "x": 269,
            "y": 677,
            "w": 122,
            "h": 54,
            "area": 6396,
            "ratio": 0.00106,
            "confidence": 1.0
        },
        {
            "x": 469,
            "y": 733,
            "w": 103,
            "h": 66,
            "area": 5897,
            "ratio": 0.000977,
            "confidence": 0.9998
        },
        {
            "x": 1931,
            "y": 785,
            "w": 115,
            "h": 142,
            "area": 11697,
            "ratio": 0.001938,
            "confidence": 0.9999
        },
        {
            "x": 449,
            "y": 852,
            "w": 98,
            "h": 35,
            "area": 3346,
            "ratio": 0.000554,
            "confidence": 0.9998
        },
        {
            "x": 293,
            "y": 865,
            "w": 30,
            "h": 31,
            "area": 921,
            "ratio": 0.000153,
            "confidence": 0.9977
        },
        {
            "x": 494,
            "y": 1330,
            "w": 18,
            "h": 29,
            "area": 436,
            "ratio": 7.2e-05,
            "confidence": 0.867
        },
        {
            "x": 1745,
            "y": 1369,
            "w": 163,
            "h": 102,
            "area": 9213,
            "ratio": 0.001526,
            "confidence": 0.9998
        },
        {
            "x": 465,
            "y": 1385,
            "w": 110,
            "h": 98,
            "area": 10419,
            "ratio": 0.001726,
            "confidence": 0.9999
        },
        {
            "x": 1973,
            "y": 1441,
            "w": 39,
            "h": 33,
            "area": 1050,
            "ratio": 0.000174,
            "confidence": 0.9913
        },
        {
            "x": 1780,
            "y": 1625,
            "w": 155,
            "h": 77,
            "area": 11245,
            "ratio": 0.001863,
            "confidence": 0.9999
        },
        {
            "x": 1709,
            "y": 1652,
            "w": 7,
            "h": 26,
            "area": 170,
            "ratio": 2.8e-05,
            "confidence": 0.9854
        },
        {
            "x": 229,
            "y": 1677,
            "w": 116,
            "h": 43,
            "area": 4699,
            "ratio": 0.000778,
            "confidence": 0.9999
        },
        {
            "x": 980,
            "y": 2140,
            "w": 108,
            "h": 103,
            "area": 10927,
            "ratio": 0.00181,
            "confidence": 1.0
        },
        {
            "x": 1773,
            "y": 2173,
            "w": 98,
            "h": 50,
            "area": 4900,
            "ratio": 0.000812,
            "confidence": 1.0
        },
        {
            "x": 1453,
            "y": 2176,
            "w": 186,
            "h": 91,
            "area": 14158,
            "ratio": 0.002346,
            "confidence": 0.9999
        },
        {
            "x": 1155,
            "y": 2311,
            "w": 124,
            "h": 53,
            "area": 4780,
            "ratio": 0.000792,
            "confidence": 1.0
        }
    ]
}