{
    "id": "kriyam_0594_C0",
    "model": "FFDN",
    "confidence": 1.0,
    "regions": [
        {
            "x": 1024,
            "y": 413,
            "w": 155,
            "h": 31,
            "area": 4016,
            "ratio": 0.000676,
            "confidence": 0.9968
        },
        {
            "x": 1192,
            "y": 413,
            "w": 11,
            "h": 23,
            "area": 216,
            "ratio": 3.6e-05,
            "confidence": 0.9652
        },
        {
            "x": 592,
            "y": 424,
            "w": 122,
            "h": 38,
            "area": 3068,
            "ratio": 0.000516,
            "confidence": 0.9637
        },
        {
            "x": 542,
            "y": 441,
            "w": 20,
            "h": 18,
            "area": 268,
            "ratio": 4.5e-05,
            "confidence": 0.8638
        },
        {
            "x": 685,
            "y": 521,
            "w": 175,
            "h": 51,
            "area": 7596,
            "ratio": 0.001279,
            "confidence": 0.9997
        },
        {
            "x": 1497,
            "y": 543,
            "w": 6,
            "h": 5,
            "area": 30,
            "ratio": 5e-06,
            "confidence": 0.9478
        },
        {
            "x": 901,
            "y": 809,
            "w": 127,
            "h": 38,
            "area": 4423,
            "ratio": 0.000745,
            "confidence": 1.0
        },
        {
            "x": 1220,
            "y": 1013,
            "w": 147,
            "h": 38,
            "area": 5023,
            "ratio": 0.000846,
            "confidence": 0.9996
        },
        {
            "x": 1264,
            "y": 1221,
            "w": 43,
            "h": 38,
            "area": 1558,
            "ratio": 0.000262,
            "confidence": 1.0
        },
        {
            "x": 321,
            "y": 1233,
            "w": 142,
            "h": 35,
            "area": 4772,
            "ratio": 0.000803,
            "confidence": 1.0
        },
        {
            "x": 1349,
            "y": 1425,
            "w": 31,
            "h": 38,
            "area": 909,
            "ratio": 0.000153,
            "confidence": 1.0
        },
        {
            "x": 1406,
            "y": 1425,
            "w": 181,
            "h": 38,
            "area": 5524,
            "ratio": 0.00093,
            "confidence": 0.997
        },
        {
            "x": 329,
            "y": 1543,
            "w": 94,
            "h": 36,
            "area": 3222,
            "ratio": 0.000542,
            "confidence": 0.9992
        },
        {
            "x": 1365,
            "y": 1737,
            "w": 174,
            "h": 37,
            "area": 5833,
            "ratio": 0.000982,
            "confidence": 1.0
        },
        {
            "x": 1213,
            "y": 1749,
            "w": 90,
            "h": 27,
            "area": 2354,
            "ratio": 0.000396,
            "confidence": 1.0
        },
        {
            "x": 1005,
            "y": 1901,
            "w": 241,
            "h": 46,
            "area": 7957,
            "ratio": 0.001339,
            "confidence": 1.0
        },
        {
            "x": 1129,
            "y": 2005,
            "w": 91,
            "h": 34,
            "area": 3036,
            "ratio": 0.000511,
            "confidence": 1.0
        },
        {
            "x": 905,
            "y": 2018,
            "w": 12,
            "h": 10,
            "area": 104,
            "ratio": 1.8e-05,
            "confidence": 0.7096
        },
        {
            "x": 878,
            "y": 2022,
            "w": 13,
            "h": 13,
            "area": 150,
            "ratio": 2.5e-05,
            "confidence": 0.7544
        },
        {
            "x": 829,
            "y": 2026,
            "w": 7,
            "h": 10,
            "area": 63,
            "ratio": 1.1e-05,
            "confidence": 0.9294
        },
        {
            "x": 1245,
            "y": 2302,
            "w": 54,
            "h": 9,
            "area": 354,
            "ratio": 6e-05,
            "confidence": 0.8804
        },
        {
            "x": 1404,
            "y": 2321,
            "w": 11,
            "h": 13,
            "area": 119,
            "ratio": 2e-05,
            "confidence": 0.9789
        },
        {
            "x": 1506,
            "y": 2345,
            "w": 10,
            "h": 6,
            "area": 54,
            "ratio": 9e-06,
            "confidence": 0.731
        },
        {
            "x": 1480,
            "y": 2346,
            "w": 5,
            "h": 5,
            "area": 25,
            "ratio": 4e-06,
            "confidence": 0.7783
        }
    ]
}