{
    "id": "kriyam_0543_C2",
    "model": "FFDN",
    "confidence": 0.8953,
    "regions": [
        {
            "x": 185,
            "y": 369,
            "w": 22,
            "h": 18,
            "area": 253,
            "ratio": 6.5e-05,
            "confidence": 0.881
        },
        {
            "x": 227,
            "y": 376,
            "w": 5,
            "h": 5,
            "area": 25,
            "ratio": 6e-06,
            "confidence": 0.741
        },
        {
            "x": 1161,
            "y": 950,
            "w": 10,
            "h": 7,
            "area": 65,
            "ratio": 1.7e-05,
            "confidence": 0.8953
        },
        {
            "x": 1192,
            "y": 962,
            "w": 19,
            "h": 5,
            "area": 95,
            "ratio": 2.5e-05,
            "confidence": 0.8351
        },
        {
            "x": 416,
            "y": 1357,
            "w": 45,
            "h": 18,
            "area": 672,
            "ratio": 0.000174,
            "confidence": 0.7523
        },
        {
            "x": 258,
            "y": 1363,
            "w": 9,
            "h": 5,
            "area": 45,
            "ratio": 1.2e-05,
            "confidence": 0.7143
        },
        {
            "x": 390,
            "y": 1873,
            "w": 11,
            "h": 7,
            "area": 65,
            "ratio": 1.7e-05,
            "confidence": 0.7196
        },
        {
            "x": 671,
            "y": 2161,
            "w": 5,
            "h": 5,
            "area": 25,
            "ratio": 6e-06,
            "confidence": 0.7923
        },
        {
            "x": 224,
            "y": 2169,
            "w": 29,
            "h": 10,
            "area": 254,
            "ratio": 6.6e-05,
            "confidence": 0.7832
        }
    ]
}