{
    "id": "kriyam_0214_C0",
    "model": "DTD",
    "is_authentic": false,
    "is_ai_generated": false,
    "confidence": 0.88818359375,
    "regions": [
        {
            "x": 620,
            "y": 215,
            "w": 9,
            "h": 8,
            "area": 65,
            "area_ratio": 0.00011063453159041394,
            "confidence": 0.58544921875
        },
        {
            "x": 877,
            "y": 215,
            "w": 4,
            "h": 3,
            "area": 12,
            "area_ratio": 2.0424836601307188e-05,
            "confidence": 0.51171875
        },
        {
            "x": 632,
            "y": 216,
            "w": 5,
            "h": 5,
            "area": 24,
            "area_ratio": 4.0849673202614376e-05,
            "confidence": 0.54296875
        },
        {
            "x": 875,
            "y": 236,
            "w": 55,
            "h": 15,
            "area": 554,
            "area_ratio": 0.000942946623093682,
            "confidence": 0.6328125
        },
        {
            "x": 937,
            "y": 239,
            "w": 4,
            "h": 10,
            "area": 36,
            "area_ratio": 6.127450980392157e-05,
            "confidence": 0.54052734375
        },
        {
            "x": 855,
            "y": 243,
            "w": 6,
            "h": 4,
            "area": 22,
            "area_ratio": 3.744553376906318e-05,
            "confidence": 0.5107421875
        },
        {
            "x": 866,
            "y": 378,
            "w": 100,
            "h": 16,
            "area": 1418,
            "area_ratio": 0.0024135348583877994,
            "confidence": 0.88818359375
        },
        {
            "x": 975,
            "y": 381,
            "w": 14,
            "h": 11,
            "area": 135,
            "area_ratio": 0.00022977941176470588,
            "confidence": 0.57958984375
        },
        {
            "x": 999,
            "y": 382,
            "w": 9,
            "h": 10,
            "area": 76,
            "area_ratio": 0.00012935729847494553,
            "confidence": 0.56005859375
        }
    ]
}