{
    "id": "kriyam_0555_C2",
    "model": "DTD",
    "is_authentic": true,
    "is_ai_generated": false,
    "confidence": 0.91064453125,
    "regions": [
        {
            "x": 504,
            "y": 918,
            "w": 8,
            "h": 30,
            "area": 230,
            "area_ratio": 3.816236593394924e-05,
            "confidence": 0.89697265625
        },
        {
            "x": 1720,
            "y": 1212,
            "w": 38,
            "h": 23,
            "area": 857,
            "area_ratio": 0.00014219629393649781,
            "confidence": 0.8115234375
        },
        {
            "x": 407,
            "y": 1216,
            "w": 58,
            "h": 30,
            "area": 1732,
            "area_ratio": 0.00028737920781565253,
            "confidence": 0.86279296875
        },
        {
            "x": 350,
            "y": 1256,
            "w": 30,
            "h": 29,
            "area": 524,
            "area_ratio": 8.694382499734523e-05,
            "confidence": 0.71826171875
        },
        {
            "x": 1446,
            "y": 1281,
            "w": 46,
            "h": 31,
            "area": 1374,
            "area_ratio": 0.0002279786556228098,
            "confidence": 0.87841796875
        },
        {
            "x": 1536,
            "y": 2807,
            "w": 16,
            "h": 38,
            "area": 594,
            "area_ratio": 9.85584581076776e-05,
            "confidence": 0.8662109375
        },
        {
            "x": 458,
            "y": 2849,
            "w": 54,
            "h": 49,
            "area": 2604,
            "area_ratio": 0.00043206435170436443,
            "confidence": 0.91064453125
        }
    ]
}