{
    "id": "kriyam_0204_C4",
    "model": "DTD",
    "is_authentic": true,
    "is_ai_generated": false,
    "confidence": 0.90576171875,
    "regions": [
        {
            "x": 1536,
            "y": 743,
            "w": 7,
            "h": 23,
            "area": 157,
            "area_ratio": 2.6049962833174047e-05,
            "confidence": 0.77978515625
        },
        {
            "x": 1559,
            "y": 742,
            "w": 44,
            "h": 37,
            "area": 1161,
            "area_ratio": 0.00019263698630136986,
            "confidence": 0.70947265625
        },
        {
            "x": 512,
            "y": 1230,
            "w": 54,
            "h": 36,
            "area": 1908,
            "area_ratio": 0.0003165817139216311,
            "confidence": 0.80712890625
        },
        {
            "x": 512,
            "y": 1532,
            "w": 3,
            "h": 3,
            "area": 9,
            "area_ratio": 1.4933099713284485e-06,
            "confidence": 0.533203125
        },
        {
            "x": 815,
            "y": 1638,
            "w": 77,
            "h": 40,
            "area": 1756,
            "area_ratio": 0.00029136136773919507,
            "confidence": 0.84228515625
        },
        {
            "x": 1044,
            "y": 1776,
            "w": 19,
            "h": 28,
            "area": 526,
            "area_ratio": 8.727567165764044e-05,
            "confidence": 0.90576171875
        },
        {
            "x": 1138,
            "y": 2100,
            "w": 40,
            "h": 35,
            "area": 935,
            "area_ratio": 0.00015513831368801104,
            "confidence": 0.818359375
        },
        {
            "x": 1219,
            "y": 2100,
            "w": 34,
            "h": 33,
            "area": 1088,
            "area_ratio": 0.00018052458320059466,
            "confidence": 0.82177734375
        }
    ]
}