{
    "id": "kriyam_0802_C0",
    "model": "DTD",
    "is_authentic": true,
    "is_ai_generated": false,
    "confidence": 0.80615234375,
    "regions": [
        {
            "x": 492,
            "y": 718,
            "w": 20,
            "h": 15,
            "area": 286,
            "area_ratio": 0.00013521998305495038,
            "confidence": 0.80615234375
        },
        {
            "x": 338,
            "y": 742,
            "w": 36,
            "h": 12,
            "area": 387,
            "area_ratio": 0.0001829724945533769,
            "confidence": 0.6845703125
        },
        {
            "x": 329,
            "y": 744,
            "w": 4,
            "h": 9,
            "area": 30,
            "area_ratio": 1.4183914306463327e-05,
            "confidence": 0.58740234375
        },
        {
            "x": 712,
            "y": 752,
            "w": 7,
            "h": 11,
            "area": 74,
            "area_ratio": 3.498698862260954e-05,
            "confidence": 0.77001953125
        },
        {
            "x": 289,
            "y": 943,
            "w": 12,
            "h": 11,
            "area": 80,
            "area_ratio": 3.78237714839022e-05,
            "confidence": 0.57177734375
        },
        {
            "x": 271,
            "y": 948,
            "w": 3,
            "h": 6,
            "area": 18,
            "area_ratio": 8.510348583877996e-06,
            "confidence": 0.556640625
        },
        {
            "x": 712,
            "y": 1094,
            "w": 11,
            "h": 20,
            "area": 214,
            "area_ratio": 0.00010117858871943839,
            "confidence": 0.66259765625
        }
    ]
}