{
    "id": "kriyam_0631_C0",
    "model": "CAFTB",
    "is_authentic": false,
    "is_ai_generated": false,
    "confidence": 1.0,
    "regions": [
        {
            "x": 54,
            "y": 202,
            "w": 691,
            "h": 914,
            "confidence": 0.29995861649513245
        },
        {
            "x": 225,
            "y": 215,
            "w": 355,
            "h": 206,
            "confidence": 0.29972153902053833
        },
        {
            "x": 626,
            "y": 725,
            "w": 179,
            "h": 98,
            "confidence": 0.2955780327320099
        },
        {
            "x": 682,
            "y": 835,
            "w": 125,
            "h": 101,
            "confidence": 0.29892823100090027
        },
        {
            "x": 139,
            "y": 1158,
            "w": 243,
            "h": 48,
            "confidence": 0.29912644624710083
        },
        {
            "x": 615,
            "y": 218,
            "w": 104,
            "h": 93,
            "confidence": 0.29981765151023865
        },
        {
            "x": 68,
            "y": 1150,
            "w": 42,
            "h": 61,
            "confidence": 0.2890135645866394
        },
        {
            "x": 129,
            "y": 1078,
            "w": 95,
            "h": 35,
            "confidence": 0.8849005103111267
        },
        {
            "x": 424,
            "y": 1200,
            "w": 70,
            "h": 13,
            "confidence": 0.2945646047592163
        },
        {
            "x": 47,
            "y": 110,
            "w": 5,
            "h": 21,
            "confidence": 0.27481117844581604
        },
        {
            "x": 617,
            "y": 222,
            "w": 8,
            "h": 7,
            "confidence": 0.6500561237335205
        },
        {
            "x": 578,
            "y": 492,
            "w": 10,
            "h": 1,
            "confidence": 0.38750073313713074
        },
        {
            "x": 129,
            "y": 992,
            "w": 5,
            "h": 4,
            "confidence": 0.4183333218097687
        }
    ]
}