{
    "id": "kriyam_0723_C2",
    "model": "CAFTB",
    "is_authentic": false,
    "is_ai_generated": false,
    "confidence": 1.0,
    "regions": [
        {
            "x": 388,
            "y": 226,
            "w": 1784,
            "h": 118,
            "confidence": 0.29957684874534607
        },
        {
            "x": 1202,
            "y": 1185,
            "w": 703,
            "h": 269,
            "confidence": 0.29844191670417786
        },
        {
            "x": 2132,
            "y": 1172,
            "w": 297,
            "h": 350,
            "confidence": 0.29859453439712524
        },
        {
            "x": 906,
            "y": 2234,
            "w": 461,
            "h": 316,
            "confidence": 0.2996637225151062
        },
        {
            "x": 1439,
            "y": 2590,
            "w": 326,
            "h": 220,
            "confidence": 0.29779356718063354
        },
        {
            "x": 1439,
            "y": 2234,
            "w": 316,
            "h": 206,
            "confidence": 0.29958227276802063
        },
        {
            "x": 2088,
            "y": 432,
            "w": 283,
            "h": 165,
            "confidence": 0.29386773705482483
        },
        {
            "x": 179,
            "y": 1178,
            "w": 282,
            "h": 132,
            "confidence": 0.2990671694278717
        },
        {
            "x": 911,
            "y": 2583,
            "w": 234,
            "h": 179,
            "confidence": 0.29903653264045715
        },
        {
            "x": 1977,
            "y": 55,
            "w": 340,
            "h": 90,
            "confidence": 0.2969919443130493
        },
        {
            "x": 1812,
            "y": 445,
            "w": 258,
            "h": 132,
            "confidence": 0.29902583360671997
        },
        {
            "x": 1163,
            "y": 2604,
            "w": 204,
            "h": 179,
            "confidence": 0.2969880700111389
        },
        {
            "x": 2214,
            "y": 767,
            "w": 205,
            "h": 186,
            "confidence": 0.2995736598968506
        },
        {
            "x": 940,
            "y": 774,
            "w": 142,
            "h": 234,
            "confidence": 0.29980018734931946
        },
        {
            "x": 257,
            "y": 2234,
            "w": 214,
            "h": 117,
            "confidence": 0.29916560649871826
        },
        {
            "x": 528,
            "y": 2234,
            "w": 166,
            "h": 158,
            "confidence": 0.2998763620853424
        },
        {
            "x": 1008,
            "y": 1823,
            "w": 146,
            "h": 233,
            "confidence": 0.29981741309165955
        },
        {
            "x": 267,
            "y": 2597,
            "w": 199,
            "h": 97,
            "confidence": 0.2977747619152069
        },
        {
            "x": 2326,
            "y": 2240,
            "w": 88,
            "h": 214,
            "confidence": 0.29903444647789
        },
        {
            "x": 727,
            "y": 2247,
            "w": 127,
            "h": 118,
            "confidence": 0.2994207441806793
        },
        {
            "x": 935,
            "y": 1199,
            "w": 156,
            "h": 76,
            "confidence": 0.294619083404541
        },
        {
            "x": 1798,
            "y": 2617,
            "w": 103,
            "h": 111,
            "confidence": 0.2989353835582733
        },
        {
            "x": 741,
            "y": 2610,
            "w": 118,
            "h": 118,
            "confidence": 0.29785263538360596
        },
        {
            "x": 1812,
            "y": 2254,
            "w": 84,
            "h": 90,
            "confidence": 0.2935906946659088
        },
        {
            "x": 179,
            "y": 2247,
            "w": 55,
            "h": 138,
            "confidence": 0.2983047366142273
        },
        {
            "x": 2321,
            "y": 2638,
            "w": 93,
            "h": 69,
            "confidence": 0.29793864488601685
        },
        {
            "x": 538,
            "y": 2631,
            "w": 49,
            "h": 90,
            "confidence": 0.29916343092918396
        },
        {
            "x": 2287,
            "y": 980,
            "w": 108,
            "h": 42,
            "confidence": 0.2996019423007965
        },
        {
            "x": 756,
            "y": 1206,
            "w": 54,
            "h": 63,
            "confidence": 0.29696571826934814
        },
        {
            "x": 383,
            "y": 774,
            "w": 83,
            "h": 49,
            "confidence": 0.298833429813385
        },
        {
            "x": 538,
            "y": 1213,
            "w": 44,
            "h": 69,
            "confidence": 0.295240581035614
        },
        {
            "x": 1323,
            "y": 459,
            "w": 64,
            "h": 49,
            "confidence": 0.29762110114097595
        },
        {
            "x": 1313,
            "y": 1473,
            "w": 74,
            "h": 56,
            "confidence": 0.29823219776153564
        },
        {
            "x": 184,
            "y": 2624,
            "w": 40,
            "h": 83,
            "confidence": 0.28900769352912903
        },
        {
            "x": 1667,
            "y": 808,
            "w": 30,
            "h": 77,
            "confidence": 0.2796096205711365
        },
        {
            "x": 640,
            "y": 2638,
            "w": 39,
            "h": 63,
            "confidence": 0.293381005525589
        },
        {
            "x": 2156,
            "y": 822,
            "w": 11,
            "h": 29,
            "confidence": 0.36400943994522095
        },
        {
            "x": 1783,
            "y": 2713,
            "w": 11,
            "h": 49,
            "confidence": 0.2953483462333679
        },
        {
            "x": 974,
            "y": 802,
            "w": 16,
            "h": 14,
            "confidence": 0.2878793179988861
        },
        {
            "x": 959,
            "y": 2288,
            "w": 1,
            "h": 1,
            "confidence": 0.30749955773353577
        }
    ]
}