{
    "id": "kriyam_0420_C2",
    "model": "CAFTB",
    "is_authentic": false,
    "is_ai_generated": false,
    "confidence": 1.0,
    "regions": [
        {
            "x": 1003,
            "y": 1830,
            "w": 945,
            "h": 412,
            "confidence": 0.2997840940952301
        },
        {
            "x": 635,
            "y": 2454,
            "w": 785,
            "h": 521,
            "confidence": 0.29983457922935486
        },
        {
            "x": 1066,
            "y": 1234,
            "w": 713,
            "h": 398,
            "confidence": 0.2972349524497986
        },
        {
            "x": 1463,
            "y": 2426,
            "w": 403,
            "h": 399,
            "confidence": 0.2994442582130432
        },
        {
            "x": 455,
            "y": 1713,
            "w": 457,
            "h": 84,
            "confidence": 0.296671599149704
        },
        {
            "x": 591,
            "y": 1097,
            "w": 282,
            "h": 76,
            "confidence": 0.2885577380657196
        },
        {
            "x": 513,
            "y": 2296,
            "w": 394,
            "h": 56,
            "confidence": 0.2953282296657562
        },
        {
            "x": 388,
            "y": 2269,
            "w": 68,
            "h": 124,
            "confidence": 0.2611650824546814
        },
        {
            "x": 1114,
            "y": 2570,
            "w": 166,
            "h": 49,
            "confidence": 0.2994743883609772
        },
        {
            "x": 1308,
            "y": 2529,
            "w": 98,
            "h": 76,
            "confidence": 0.28589755296707153
        },
        {
            "x": 489,
            "y": 1083,
            "w": 54,
            "h": 63,
            "confidence": 0.2542892396450043
        },
        {
            "x": 1061,
            "y": 2474,
            "w": 64,
            "h": 56,
            "confidence": 0.29983457922935486
        },
        {
            "x": 349,
            "y": 1028,
            "w": 44,
            "h": 76,
            "confidence": 0.260120153427124
        }
    ]
}