{
    "id": "kriyam_0325_C2",
    "model": "CAFTB",
    "is_authentic": false,
    "is_ai_generated": false,
    "confidence": 1.0,
    "regions": [
        {
            "x": 78,
            "y": 658,
            "w": 2016,
            "h": 2378,
            "confidence": 0.2998916804790497
        },
        {
            "x": 417,
            "y": 713,
            "w": 282,
            "h": 281,
            "confidence": 0.2998916804790497
        },
        {
            "x": 107,
            "y": 582,
            "w": 238,
            "h": 180,
            "confidence": 0.2989678382873535
        },
        {
            "x": 1066,
            "y": 2974,
            "w": 277,
            "h": 28,
            "confidence": 0.29984936118125916
        },
        {
            "x": 1381,
            "y": 2994,
            "w": 59,
            "h": 1,
            "confidence": 0.33497345447540283
        },
        {
            "x": 940,
            "y": 884,
            "w": 30,
            "h": 15,
            "confidence": 0.2964339554309845
        },
        {
            "x": 233,
            "y": 733,
            "w": 15,
            "h": 22,
            "confidence": 0.29789498448371887
        },
        {
            "x": 751,
            "y": 740,
            "w": 11,
            "h": 15,
            "confidence": 0.2893916666507721
        },
        {
            "x": 1618,
            "y": 445,
            "w": 11,
            "h": 8,
            "confidence": 0.3603406846523285
        },
        {
            "x": 1018,
            "y": 891,
            "w": 15,
            "h": 1,
            "confidence": 0.32964515686035156
        },
        {
            "x": 761,
            "y": 336,
            "w": 10,
            "h": 1,
            "confidence": 0.31395062804222107
        },
        {
            "x": 1618,
            "y": 397,
            "w": 1,
            "h": 1,
            "confidence": 0.34892621636390686
        }
    ]
}