{
    "id": "kriyam_0967_C4",
    "model": "CAFTB",
    "is_authentic": false,
    "is_ai_generated": false,
    "confidence": 0.9999996423721313,
    "regions": [
        {
            "x": 535,
            "y": 959,
            "w": 93,
            "h": 41,
            "confidence": 0.2972666919231415
        },
        {
            "x": 388,
            "y": 1019,
            "w": 80,
            "h": 40,
            "confidence": 0.2921202778816223
        },
        {
            "x": 217,
            "y": 269,
            "w": 90,
            "h": 28,
            "confidence": 0.2990768849849701
        },
        {
            "x": 396,
            "y": 147,
            "w": 43,
            "h": 31,
            "confidence": 0.2993578016757965
        },
        {
            "x": 270,
            "y": 1021,
            "w": 44,
            "h": 23,
            "confidence": 0.29705870151519775
        },
        {
            "x": 426,
            "y": 520,
            "w": 42,
            "h": 24,
            "confidence": 0.2997370958328247
        },
        {
            "x": 526,
            "y": 147,
            "w": 42,
            "h": 21,
            "confidence": 0.2846457362174988
        },
        {
            "x": 382,
            "y": 515,
            "w": 26,
            "h": 29,
            "confidence": 0.9010101556777954
        },
        {
            "x": 458,
            "y": 75,
            "w": 31,
            "h": 23,
            "confidence": 0.29779601097106934
        },
        {
            "x": 460,
            "y": 149,
            "w": 21,
            "h": 26,
            "confidence": 0.28920823335647583
        },
        {
            "x": 598,
            "y": 154,
            "w": 42,
            "h": 16,
            "confidence": 0.2974497377872467
        },
        {
            "x": 621,
            "y": 700,
            "w": 25,
            "h": 18,
            "confidence": 0.2994888424873352
        },
        {
            "x": 349,
            "y": 515,
            "w": 24,
            "h": 21,
            "confidence": 0.2953309714794159
        },
        {
            "x": 500,
            "y": 149,
            "w": 20,
            "h": 16,
            "confidence": 0.2994517385959625
        },
        {
            "x": 144,
            "y": 1026,
            "w": 23,
            "h": 13,
            "confidence": 0.2905966639518738
        },
        {
            "x": 193,
            "y": 349,
            "w": 37,
            "h": 11,
            "confidence": 0.29589930176734924
        },
        {
            "x": 359,
            "y": 1031,
            "w": 16,
            "h": 18,
            "confidence": 0.6285122036933899
        },
        {
            "x": 204,
            "y": 740,
            "w": 23,
            "h": 11,
            "confidence": 0.29838842153549194
        },
        {
            "x": 659,
            "y": 152,
            "w": 11,
            "h": 21,
            "confidence": 0.5489177107810974
        },
        {
            "x": 100,
            "y": 827,
            "w": 20,
            "h": 11,
            "confidence": 0.2899013161659241
        },
        {
            "x": 120,
            "y": 391,
            "w": 20,
            "h": 8,
            "confidence": 0.28091925382614136
        },
        {
            "x": 271,
            "y": 1068,
            "w": 14,
            "h": 11,
            "confidence": 0.2931196093559265
        },
        {
            "x": 207,
            "y": 1068,
            "w": 11,
            "h": 11,
            "confidence": 0.2939838171005249
        },
        {
            "x": 539,
            "y": 391,
            "w": 13,
            "h": 8,
            "confidence": 0.2942246198654175
        },
        {
            "x": 519,
            "y": 518,
            "w": 11,
            "h": 6,
            "confidence": 0.28256431221961975
        },
        {
            "x": 434,
            "y": 829,
            "w": 15,
            "h": 4,
            "confidence": 0.29339107871055603
        },
        {
            "x": 470,
            "y": 747,
            "w": 9,
            "h": 9,
            "confidence": 0.25932374596595764
        },
        {
            "x": 416,
            "y": 829,
            "w": 11,
            "h": 6,
            "confidence": 0.2773454785346985
        },
        {
            "x": 437,
            "y": 82,
            "w": 6,
            "h": 9,
            "confidence": 0.7304569482803345
        },
        {
            "x": 567,
            "y": 349,
            "w": 5,
            "h": 8,
            "confidence": 0.27165111899375916
        },
        {
            "x": 85,
            "y": 575,
            "w": 5,
            "h": 9,
            "confidence": 0.28315699100494385
        },
        {
            "x": 599,
            "y": 745,
            "w": 6,
            "h": 8,
            "confidence": 0.29571640491485596
        },
        {
            "x": 167,
            "y": 1068,
            "w": 11,
            "h": 4,
            "confidence": 0.28650620579719543
        },
        {
            "x": 271,
            "y": 354,
            "w": 7,
            "h": 6,
            "confidence": 0.40519651770591736
        },
        {
            "x": 551,
            "y": 697,
            "w": 7,
            "h": 6,
            "confidence": 0.2829573154449463
        },
        {
            "x": 385,
            "y": 789,
            "w": 7,
            "h": 4,
            "confidence": 0.2973365783691406
        },
        {
            "x": 486,
            "y": 560,
            "w": 6,
            "h": 6,
            "confidence": 0.29707783460617065
        },
        {
            "x": 608,
            "y": 710,
            "w": 7,
            "h": 3,
            "confidence": 0.2941815257072449
        },
        {
            "x": 85,
            "y": 234,
            "w": 2,
            "h": 9,
            "confidence": 0.4206888973712921
        },
        {
            "x": 205,
            "y": 291,
            "w": 5,
            "h": 4,
            "confidence": 0.35672852396965027
        },
        {
            "x": 294,
            "y": 351,
            "w": 6,
            "h": 4,
            "confidence": 0.29827386140823364
        },
        {
            "x": 229,
            "y": 869,
            "w": 3,
            "h": 6,
            "confidence": 0.2975662052631378
        },
        {
            "x": 192,
            "y": 563,
            "w": 7,
            "h": 1,
            "confidence": 0.3805757761001587
        },
        {
            "x": 324,
            "y": 291,
            "w": 2,
            "h": 4,
            "confidence": 0.3930066227912903
        },
        {
            "x": 234,
            "y": 351,
            "w": 3,
            "h": 4,
            "confidence": 0.3498212695121765
        },
        {
            "x": 662,
            "y": 702,
            "w": 3,
            "h": 6,
            "confidence": 0.38353097438812256
        },
        {
            "x": 283,
            "y": 152,
            "w": 2,
            "h": 3,
            "confidence": 0.3714175522327423
        },
        {
            "x": 242,
            "y": 969,
            "w": 2,
            "h": 3,
            "confidence": 0.346660315990448
        },
        {
            "x": 580,
            "y": 832,
            "w": 3,
            "h": 1,
            "confidence": 0.3569938838481903
        },
        {
            "x": 565,
            "y": 523,
            "w": 1,
            "h": 1,
            "confidence": 0.3242262303829193
        },
        {
            "x": 640,
            "y": 523,
            "w": 1,
            "h": 1,
            "confidence": 0.30268722772598267
        }
    ]
}