{
    "id": "kriyam_0649_C4",
    "model": "CAFTB",
    "is_authentic": false,
    "is_ai_generated": false,
    "confidence": 1.0,
    "regions": [
        {
            "x": 444,
            "y": 885,
            "w": 1491,
            "h": 1132,
            "confidence": 0.2999703586101532
        },
        {
            "x": 339,
            "y": 2187,
            "w": 696,
            "h": 521,
            "confidence": 0.29977816343307495
        },
        {
            "x": 323,
            "y": 1879,
            "w": 663,
            "h": 269,
            "confidence": 0.2998943626880646
        },
        {
            "x": 1151,
            "y": 2284,
            "w": 457,
            "h": 127,
            "confidence": 0.2978639602661133
        },
        {
            "x": 852,
            "y": 657,
            "w": 384,
            "h": 86,
            "confidence": 0.2998058795928955
        },
        {
            "x": 1688,
            "y": 1239,
            "w": 235,
            "h": 93,
            "confidence": 0.2979428470134735
        },
        {
            "x": 307,
            "y": 702,
            "w": 384,
            "h": 64,
            "confidence": 0.2986590564250946
        },
        {
            "x": 396,
            "y": 2370,
            "w": 37,
            "h": 304,
            "confidence": 0.29977816343307495
        },
        {
            "x": 1179,
            "y": 577,
            "w": 199,
            "h": 58,
            "confidence": 0.29344436526298523
        },
        {
            "x": 444,
            "y": 1331,
            "w": 110,
            "h": 46,
            "confidence": 0.2903382182121277
        },
        {
            "x": 517,
            "y": 1491,
            "w": 61,
            "h": 41,
            "confidence": 0.28924039006233215
        },
        {
            "x": 771,
            "y": 1182,
            "w": 94,
            "h": 24,
            "confidence": 0.29439929127693176
        },
        {
            "x": 824,
            "y": 891,
            "w": 61,
            "h": 12,
            "confidence": 0.2954399585723877
        },
        {
            "x": 747,
            "y": 1188,
            "w": 17,
            "h": 24,
            "confidence": 0.6031030416488647
        },
        {
            "x": 1482,
            "y": 1965,
            "w": 13,
            "h": 23,
            "confidence": 0.28993818163871765
        },
        {
            "x": 1599,
            "y": 2444,
            "w": 9,
            "h": 24,
            "confidence": 0.29452505707740784
        },
        {
            "x": 525,
            "y": 1131,
            "w": 13,
            "h": 1,
            "confidence": 0.3209705054759979
        },
        {
            "x": 1603,
            "y": 2519,
            "w": 9,
            "h": 1,
            "confidence": 0.3596866726875305
        },
        {
            "x": 1187,
            "y": 1885,
            "w": 5,
            "h": 1,
            "confidence": 0.36138761043548584
        },
        {
            "x": 1231,
            "y": 1885,
            "w": 1,
            "h": 1,
            "confidence": 0.3691747188568115
        }
    ]
}