{
    "id": "kriyam_0627_C0",
    "model": "ADCD",
    "is_authentic": false,
    "is_ai_generated": false,
    "confidence": 0.8813440799713135,
    "regions": [
        {
            "x": 767,
            "y": 1320,
            "w": 23,
            "h": 15,
            "confidence": 0.505295991897583,
            "area": 65
        },
        {
            "x": 890,
            "y": 1320,
            "w": 82,
            "h": 21,
            "confidence": 0.49291878938674927,
            "area": 348
        },
        {
            "x": 917,
            "y": 1490,
            "w": 113,
            "h": 23,
            "confidence": 0.5756098628044128,
            "area": 751
        },
        {
            "x": 1653,
            "y": 1645,
            "w": 206,
            "h": 92,
            "confidence": 0.8616360425949097,
            "area": 4649
        },
        {
            "x": 1735,
            "y": 1799,
            "w": 149,
            "h": 131,
            "confidence": 0.71666419506073,
            "area": 5478
        },
        {
            "x": 241,
            "y": 2117,
            "w": 2,
            "h": 21,
            "confidence": 0.5243564248085022,
            "area": 14
        },
        {
            "x": 1650,
            "y": 2624,
            "w": 180,
            "h": 33,
            "confidence": 0.8813440799713135,
            "area": 1831
        }
    ]
}