{
    "id": "kriyam_0415_C2",
    "model": "ADCD",
    "is_authentic": true,
    "is_ai_generated": false,
    "confidence": 0.7788438200950623,
    "regions": [
        {
            "x": 1822,
            "y": 741,
            "w": 14,
            "h": 8,
            "confidence": 0.5448082089424133,
            "area": 23
        },
        {
            "x": 1897,
            "y": 759,
            "w": 29,
            "h": 183,
            "confidence": 0.5659942626953125,
            "area": 743
        },
        {
            "x": 1360,
            "y": 1893,
            "w": 18,
            "h": 16,
            "confidence": 0.5137401223182678,
            "area": 63
        },
        {
            "x": 507,
            "y": 2088,
            "w": 31,
            "h": 137,
            "confidence": 0.5178858637809753,
            "area": 665
        },
        {
            "x": 1677,
            "y": 2094,
            "w": 32,
            "h": 69,
            "confidence": 0.5556661486625671,
            "area": 381
        },
        {
            "x": 1691,
            "y": 2384,
            "w": 34,
            "h": 34,
            "confidence": 0.6987631916999817,
            "area": 238
        },
        {
            "x": 1691,
            "y": 2494,
            "w": 47,
            "h": 137,
            "confidence": 0.7702435255050659,
            "area": 1322
        },
        {
            "x": 1857,
            "y": 2575,
            "w": 107,
            "h": 106,
            "confidence": 0.7181087136268616,
            "area": 1195
        },
        {
            "x": 1859,
            "y": 2761,
            "w": 43,
            "h": 25,
            "confidence": 0.7788438200950623,
            "area": 219
        },
        {
            "x": 1364,
            "y": 2866,
            "w": 40,
            "h": 65,
            "confidence": 0.5301352143287659,
            "area": 440
        }
    ]
}