{
    "id": "kriyam_0254_C0",
    "model": "ADCD",
    "is_authentic": true,
    "is_ai_generated": false,
    "confidence": 0.6764240264892578,
    "regions": [
        {
            "x": 655,
            "y": 586,
            "w": 167,
            "h": 41,
            "confidence": 0.5834410786628723,
            "area": 1933
        },
        {
            "x": 602,
            "y": 801,
            "w": 66,
            "h": 23,
            "confidence": 0.49307695031166077,
            "area": 233
        },
        {
            "x": 294,
            "y": 808,
            "w": 5,
            "h": 12,
            "confidence": 0.5005107522010803,
            "area": 12
        },
        {
            "x": 56,
            "y": 1221,
            "w": 71,
            "h": 21,
            "confidence": 0.4994224011898041,
            "area": 314
        },
        {
            "x": 211,
            "y": 1219,
            "w": 100,
            "h": 34,
            "confidence": 0.5561844110488892,
            "area": 841
        },
        {
            "x": 676,
            "y": 1270,
            "w": 131,
            "h": 30,
            "confidence": 0.5493013858795166,
            "area": 1048
        },
        {
            "x": 806,
            "y": 1358,
            "w": 23,
            "h": 25,
            "confidence": 0.5059345960617065,
            "area": 140
        },
        {
            "x": 707,
            "y": 1360,
            "w": 60,
            "h": 21,
            "confidence": 0.49794286489486694,
            "area": 141
        },
        {
            "x": 1212,
            "y": 1528,
            "w": 24,
            "h": 21,
            "confidence": 0.5101742148399353,
            "area": 84
        },
        {
            "x": 936,
            "y": 1604,
            "w": 37,
            "h": 26,
            "confidence": 0.6134878396987915,
            "area": 313
        },
        {
            "x": 1627,
            "y": 1856,
            "w": 13,
            "h": 19,
            "confidence": 0.5232827663421631,
            "area": 66
        },
        {
            "x": 869,
            "y": 1896,
            "w": 68,
            "h": 22,
            "confidence": 0.519830584526062,
            "area": 396
        },
        {
            "x": 550,
            "y": 1912,
            "w": 1,
            "h": 1,
            "confidence": 0.5028308033943176,
            "area": 1
        },
        {
            "x": 1639,
            "y": 1957,
            "w": 32,
            "h": 26,
            "confidence": 0.5062744617462158,
            "area": 192
        },
        {
            "x": 595,
            "y": 1995,
            "w": 61,
            "h": 24,
            "confidence": 0.5122573375701904,
            "area": 322
        },
        {
            "x": 1082,
            "y": 2446,
            "w": 50,
            "h": 23,
            "confidence": 0.5100533366203308,
            "area": 220
        },
        {
            "x": 1629,
            "y": 2466,
            "w": 1,
            "h": 1,
            "confidence": 0.501110315322876,
            "area": 1
        },
        {
            "x": 1207,
            "y": 2682,
            "w": 195,
            "h": 30,
            "confidence": 0.6764240264892578,
            "area": 1796
        }
    ]
}