{
    "id": "kriyam_1028_C0",
    "model": "ADCD",
    "is_authentic": true,
    "is_ai_generated": false,
    "confidence": 0.5446697473526001,
    "regions": [
        {
            "x": 366,
            "y": 130,
            "w": 17,
            "h": 12,
            "confidence": 0.522782564163208,
            "area": 177
        },
        {
            "x": 424,
            "y": 170,
            "w": 21,
            "h": 6,
            "confidence": 0.5076091885566711,
            "area": 76
        },
        {
            "x": 212,
            "y": 191,
            "w": 19,
            "h": 4,
            "confidence": 0.49337178468704224,
            "area": 22
        },
        {
            "x": 225,
            "y": 283,
            "w": 12,
            "h": 12,
            "confidence": 0.523935854434967,
            "area": 139
        },
        {
            "x": 258,
            "y": 282,
            "w": 12,
            "h": 13,
            "confidence": 0.5347867608070374,
            "area": 145
        },
        {
            "x": 290,
            "y": 283,
            "w": 13,
            "h": 13,
            "confidence": 0.5286591053009033,
            "area": 149
        },
        {
            "x": 37,
            "y": 361,
            "w": 40,
            "h": 9,
            "confidence": 0.5446697473526001,
            "area": 356
        },
        {
            "x": 300,
            "y": 621,
            "w": 22,
            "h": 7,
            "confidence": 0.4966718554496765,
            "area": 82
        }
    ]
}